{"post_data":{"ID":444,"post_author":"2","post_date":"2014-04-14 14:47:52","post_date_gmt":"2014-04-14 14:47:52","post_content":"","post_title":"Profile OtS - App","post_excerpt":"","post_status":"private","comment_status":"closed","ping_status":"closed","post_password":"","post_name":"flat-design","to_ping":"","pinged":"","post_modified":"2015-09-10 22:16:31","post_modified_gmt":"2015-09-10 22:16:31","post_content_filtered":"","post_parent":0,"guid":"http:\/\/dev.shapingrain.com\/offtheshelfwp\/?post_type=profile&#038;p=444","menu_order":0,"post_type":"profile","post_mime_type":"","comment_count":"0","filter":"raw","ancestors":[],"post_category":[],"tags_input":[]},"post_meta":{"_edit_last":["2"],"_edit_lock":["1441923415:2"],"sr_ots_color_body_text":["#000000"],"social_media_profiles":["a:2:{i:0;a:6:{s:6:\"preset\";s:0:\"\";s:5:\"title\";s:8:\"Facebook\";s:4:\"link\";s:1:\"#\";s:4:\"icon\";s:11:\"fa-facebook\";s:16:\"color_background\";s:7:\"#c6078d\";s:14:\"show_in_header\";s:2:\"on\";}i:1;a:6:{s:6:\"preset\";s:7:\"twitter\";s:5:\"title\";s:7:\"Twitter\";s:4:\"link\";s:31:\"http:\/\/www.twitter.com\/username\";s:4:\"icon\";s:10:\"fa-twitter\";s:16:\"color_background\";s:7:\"#1bb2e9\";s:14:\"show_in_header\";s:2:\"on\";}}"],"sr_ots_header_multipurpose_social":["on"],"sr_ots_menu_link":["#ffffff"],"sr_ots_font_banner_title":["a:4:{s:4:\"size\";s:4:\"64px\";s:4:\"face\";s:6:\"ubuntu\";s:6:\"weight\";s:3:\"300\";s:5:\"color\";s:7:\"#ffffff\";}"],"sr_ots_font_banner_sub_title":["a:4:{s:4:\"size\";s:4:\"28px\";s:4:\"face\";s:6:\"ubuntu\";s:6:\"weight\";s:3:\"300\";s:5:\"color\";s:7:\"#ffffff\";}"],"sr_ots_post_format_background":["#dca400"],"sr_ots_post_format_text":["#ffffff"],"sr_ots_font_call_to_action":["a:4:{s:4:\"size\";s:4:\"18px\";s:4:\"face\";s:9:\"helvetica\";s:6:\"weight\";s:4:\"bold\";s:5:\"color\";s:1:\"0\";}"],"sr_ots_font_pricing_call_to_action":["a:4:{s:4:\"size\";s:4:\"13px\";s:4:\"face\";s:9:\"helvetica\";s:6:\"weight\";s:7:\"regular\";s:5:\"color\";s:1:\"0\";}"],"sr_ots_cta_radius":["5px"],"sr_ots_cta_default_background_mode":["solid"],"sr_ots_cta_default_color_1":["#96d600"],"sr_ots_cta_default_color_2":["#ffffff"],"sr_ots_cta_default_color_text":["#ffffff"],"sr_ots_cta_hover_background_mode":["solid"],"sr_ots_cta_hover_color_1":["#82b900"],"sr_ots_cta_hover_color_2":["#ffffff"],"sr_ots_cta_hover_color_text":["#ffffff"],"sr_ots_design_banner":["0"],"sr_ots_navigation_background":["#e77e2a"],"sr_ots_navigation_text":["#ffffff"],"sr_ots_navigation_background_hover":["#e87212"],"sr_ots_navigation_text_hover":["#ffffff"],"slide_template":["default"],"sr_ots_show_search_bar":["on"],"sr_ots_content_layout":["default"],"sr_ots_body_background_mode":["solid"],"sr_ots_color_body_background":["#ffffff"],"sr_ots_color_body_background_boxed_wrapper":["#f5f5f5"],"sr_ots_color_body_link":["#e4473c"],"sr_ots_color_body_link_hover":["#d13c2b"],"sr_ots_default_button_style":["55f1e7dcf2cb7"],"sr_ots_font_body":["a:4:{s:4:\"size\";s:4:\"16px\";s:4:\"face\";s:4:\"lato\";s:6:\"weight\";s:7:\"regular\";s:5:\"color\";s:7:\"#333333\";}"],"sr_ots_font_logo":["a:4:{s:4:\"size\";s:4:\"28px\";s:4:\"face\";s:4:\"lato\";s:6:\"weight\";s:7:\"regular\";s:5:\"color\";s:7:\"#777777\";}"],"sr_ots_font_logo_tagline":["a:4:{s:4:\"size\";s:4:\"16px\";s:4:\"face\";s:4:\"lato\";s:6:\"weight\";s:6:\"italic\";s:5:\"color\";s:7:\"#c1c1c1\";}"],"sr_ots_font_page_title":["a:4:{s:4:\"size\";s:4:\"13px\";s:4:\"face\";s:4:\"lato\";s:6:\"weight\";s:7:\"regular\";s:5:\"color\";s:7:\"#333333\";}"],"sr_ots_font_widget_title":["a:4:{s:4:\"size\";s:4:\"13px\";s:4:\"face\";s:4:\"lato\";s:6:\"weight\";s:7:\"regular\";s:5:\"color\";s:7:\"#333333\";}"],"sr_ots_font_quote":["a:4:{s:4:\"size\";s:4:\"18px\";s:4:\"face\";s:4:\"lato\";s:6:\"weight\";s:9:\"300italic\";s:5:\"color\";s:7:\"#333333\";}"],"sr_ots_font_h1":["a:4:{s:4:\"size\";s:4:\"41px\";s:4:\"face\";s:4:\"lato\";s:6:\"weight\";s:3:\"300\";s:5:\"color\";s:7:\"#333333\";}"],"sr_ots_font_h2":["a:4:{s:4:\"size\";s:4:\"34px\";s:4:\"face\";s:4:\"lato\";s:6:\"weight\";s:3:\"300\";s:5:\"color\";s:7:\"#333333\";}"],"sr_ots_font_h3":["a:4:{s:4:\"size\";s:4:\"24px\";s:4:\"face\";s:4:\"lato\";s:6:\"weight\";s:3:\"300\";s:5:\"color\";s:7:\"#333333\";}"],"sr_ots_font_h4":["a:4:{s:4:\"size\";s:4:\"20px\";s:4:\"face\";s:4:\"lato\";s:6:\"weight\";s:3:\"300\";s:5:\"color\";s:7:\"#333333\";}"],"sr_ots_font_h5":["a:4:{s:4:\"size\";s:4:\"13px\";s:4:\"face\";s:4:\"lato\";s:6:\"weight\";s:3:\"300\";s:5:\"color\";s:7:\"#333333\";}"],"sr_ots_font_h6":["a:4:{s:4:\"size\";s:4:\"11px\";s:4:\"face\";s:4:\"lato\";s:6:\"weight\";s:3:\"300\";s:5:\"color\";s:7:\"#333333\";}"],"sr_ots_header_menu_transparent":["on"],"sr_ots_header_logo_image":["a:2:{s:2:\"id\";s:4:\"5907\";s:3:\"url\";s:93:\"http:\/\/dev.shapingrain.com\/offtheshelfwp\/wp-content\/uploads\/sites\/6\/2015\/09\/logo_app_time.png\";}"],"sr_ots_header_tagline_hide":["on"],"sr_ots_header_title":["OnTime"],"sr_ots_header_background":["#ffffff"],"sr_ots_header_text":["#828282"],"sr_ots_menu_link_hover":["#e4473c"],"sr_ots_header_sub_banner_color_background":["#f5f5f5"],"sr_ots_header_sub_banner_color_text":["#afafaf"],"sr_ots_header_multipurpose_mode":["content"],"sr_ots_header_multipurpose_custom":["<p style=\"text-align: right;\">Give us a call under 0101010 - 010240410<\/p>"],"sr_ots_header_multipurpose_background":["#f5f5f5"],"sr_ots_header_multipurpose_text":["#afafaf"],"sr_ots_footer_copyright":["Made with love by <a href=\"http:\/\/www.shapingrain.com\/\">ShapingRain<\/a> and WordPress"],"sr_ots_footer_background":["#2f2f2f"],"sr_ots_footer_text":["#a0a0a0"],"sr_ots_subfooter_background":["#f5f5f5"],"sr_ots_subfooter_text":["#a0a0a0"]}}